ctconvert/__init__.py
ctconvert/bigquery.py
ctconvert/convert_data.py
ctconvert/create_instance.py
ctconvert/fdaaa_regulatory_snapshot.csv.gz
ctconvert/startup_script.sh
ctconvert/tests/__init__.py
ctconvert/tests/test_convert_data.py
ctconvert/tests/fixtures/data.zip
ctconvert/tests/fixtures/expected_trials_data.csv
ctconvert/tests/fixtures/expected_trials_json.json
ctconvert-0.0.2.dist-info/WHEEL
ctconvert-0.0.2.dist-info/METADATA
ctconvert-0.0.2.dist-info/RECORD
