Metadata-Version: 2.1
Name: ctconvert
Version: 0.0.2
Summary: Tools to convert CT.gov XML to a CSV
Home-page: https://github.com/ebmdatalab/clinicaltrials-act-converter
License: UNKNOWN
Author: EBM DataLab
Author-email: tech@ebmdatalab.net
Classifier: License :: OSI Approved :: MIT License
Requires-Dist: requests
Requires-Dist: google-api-python-client
Requires-Dist: google-cloud-bigquery
Requires-Dist: google-cloud-storage
Requires-Dist: xmltodict
Requires-Dist: lxml
Requires-Dist: bs4
Requires-Dist: python-dateutil
